<annotation>
	<folder>data</folder>
	<filename>5e95668b59b89.jpg</filename>
	<path>C:\Users\Thomas\Desktop\!CAPTCHA\data\5e95668b59b89.jpg</path>
	<source>
		<database>Unknown</database>
	</source>
	<size>
		<width>800</width>
		<height>200</height>
		<depth>1</depth>
	</size>
	<segmented>0</segmented>
	<object>
		<name>b</name>
		<pose>Unspecified</pose>
		<truncated>0</truncated>
		<difficult>0</difficult>
		<bndbox>
			<xmin>234</xmin>
			<ymin>49</ymin>
			<xmax>325</xmax>
			<ymax>150</ymax>
		</bndbox>
	</object>
	<object>
		<name>u</name>
		<pose>Unspecified</pose>
		<truncated>0</truncated>
		<difficult>0</difficult>
		<bndbox>
			<xmin>328</xmin>
			<ymin>77</ymin>
			<xmax>400</xmax>
			<ymax>144</ymax>
		</bndbox>
	</object>
	<object>
		<name>n</name>
		<pose>Unspecified</pose>
		<truncated>0</truncated>
		<difficult>0</difficult>
		<bndbox>
			<xmin>400</xmin>
			<ymin>75</ymin>
			<xmax>478</xmax>
			<ymax>146</ymax>
		</bndbox>
	</object>
	<object>
		<name>d</name>
		<pose>Unspecified</pose>
		<truncated>0</truncated>
		<difficult>0</difficult>
		<bndbox>
			<xmin>478</xmin>
			<ymin>54</ymin>
			<xmax>567</xmax>
			<ymax>143</ymax>
		</bndbox>
	</object>
	<object>
		<name>t</name>
		<pose>Unspecified</pose>
		<truncated>0</truncated>
		<difficult>0</difficult>
		<bndbox>
			<xmin>565</xmin>
			<ymin>54</ymin>
			<xmax>624</xmax>
			<ymax>145</ymax>
		</bndbox>
	</object>
	<object>
		<name>s</name>
		<pose>Unspecified</pose>
		<truncated>0</truncated>
		<difficult>0</difficult>
		<bndbox>
			<xmin>625</xmin>
			<ymin>71</ymin>
			<xmax>696</xmax>
			<ymax>144</ymax>
		</bndbox>
	</object>
</annotation>
