<annotation>
	<folder>CAPTCHA_images</folder>
	<filename>5e95a03241900.jpg</filename>
	<path>/home/theotheu/workspaces/sci-hub-captcha-solver/CAPTCHA_images/5e95a03241900.jpg</path>
	<source>
		<database>Unknown</database>
	</source>
	<size>
		<width>800</width>
		<height>200</height>
		<depth>1</depth>
	</size>
	<segmented>0</segmented>
	<object>
		<name>d</name>
		<pose>Unspecified</pose>
		<truncated>0</truncated>
		<difficult>0</difficult>
		<bndbox>
			<xmin>330</xmin>
			<ymin>53</ymin>
			<xmax>407</xmax>
			<ymax>147</ymax>
		</bndbox>
	</object>
	<object>
		<name>i</name>
		<pose>Unspecified</pose>
		<truncated>0</truncated>
		<difficult>0</difficult>
		<bndbox>
			<xmin>405</xmin>
			<ymin>51</ymin>
			<xmax>446</xmax>
			<ymax>147</ymax>
		</bndbox>
	</object>
	<object>
		<name>d</name>
		<pose>Unspecified</pose>
		<truncated>0</truncated>
		<difficult>0</difficult>
		<bndbox>
			<xmin>442</xmin>
			<ymin>48</ymin>
			<xmax>531</xmax>
			<ymax>148</ymax>
		</bndbox>
	</object>
	<object>
		<name>a</name>
		<pose>Unspecified</pose>
		<truncated>0</truncated>
		<difficult>0</difficult>
		<bndbox>
			<xmin>533</xmin>
			<ymin>69</ymin>
			<xmax>609</xmax>
			<ymax>149</ymax>
		</bndbox>
	</object>
	<object>
		<name>c</name>
		<pose>Unspecified</pose>
		<truncated>0</truncated>
		<difficult>0</difficult>
		<bndbox>
			<xmin>611</xmin>
			<ymin>67</ymin>
			<xmax>682</xmax>
			<ymax>145</ymax>
		</bndbox>
	</object>
	<object>
		<name>t</name>
		<pose>Unspecified</pose>
		<truncated>0</truncated>
		<difficult>0</difficult>
		<bndbox>
			<xmin>682</xmin>
			<ymin>58</ymin>
			<xmax>743</xmax>
			<ymax>145</ymax>
		</bndbox>
	</object>
</annotation>
