<annotation>
	<folder>data</folder>
	<filename>5e960534d9b74.jpg</filename>
	<path>C:\Users\Thomas\Desktop\!CAPTCHA\data\5e960534d9b74.jpg</path>
	<source>
		<database>Unknown</database>
	</source>
	<size>
		<width>800</width>
		<height>200</height>
		<depth>1</depth>
	</size>
	<segmented>0</segmented>
	<object>
		<name>p</name>
		<pose>Unspecified</pose>
		<truncated>0</truncated>
		<difficult>0</difficult>
		<bndbox>
			<xmin>312</xmin>
			<ymin>52</ymin>
			<xmax>404</xmax>
			<ymax>149</ymax>
		</bndbox>
	</object>
	<object>
		<name>a</name>
		<pose>Unspecified</pose>
		<truncated>0</truncated>
		<difficult>0</difficult>
		<bndbox>
			<xmin>403</xmin>
			<ymin>50</ymin>
			<xmax>489</xmax>
			<ymax>129</ymax>
		</bndbox>
	</object>
	<object>
		<name>t</name>
		<pose>Unspecified</pose>
		<truncated>0</truncated>
		<difficult>0</difficult>
		<bndbox>
			<xmin>489</xmin>
			<ymin>39</ymin>
			<xmax>545</xmax>
			<ymax>122</ymax>
		</bndbox>
	</object>
	<object>
		<name>h</name>
		<pose>Unspecified</pose>
		<truncated>0</truncated>
		<difficult>0</difficult>
		<bndbox>
			<xmin>542</xmin>
			<ymin>34</ymin>
			<xmax>631</xmax>
			<ymax>122</ymax>
		</bndbox>
	</object>
	<object>
		<name>o</name>
		<pose>Unspecified</pose>
		<truncated>0</truncated>
		<difficult>0</difficult>
		<bndbox>
			<xmin>628</xmin>
			<ymin>49</ymin>
			<xmax>709</xmax>
			<ymax>124</ymax>
		</bndbox>
	</object>
	<object>
		<name>s</name>
		<pose>Unspecified</pose>
		<truncated>0</truncated>
		<difficult>0</difficult>
		<bndbox>
			<xmin>708</xmin>
			<ymin>47</ymin>
			<xmax>778</xmax>
			<ymax>126</ymax>
		</bndbox>
	</object>
</annotation>
